flasche/__init__.py
flasche/build.py
flasche/cli.py
flasche/flasksetup.py
flasche/run.py
flasche/templates/flasche.py
flasche/templates/main.py
flasche/templates/endpoints/__init__.py
flasche/templates/endpoints/test_endpoint.py
flasche-0.0.3.dist-info/LICENSE
flasche-0.0.3.dist-info/METADATA
flasche-0.0.3.dist-info/WHEEL
flasche-0.0.3.dist-info/entry_points.txt
flasche-0.0.3.dist-info/top_level.txt
flasche-0.0.3.dist-info/RECORD
