Metadata-Version: 2.1
Name: flasche
Version: 0.0.3
Summary: flasche extends flask by prometheus-flask-exporter and swagger
Home-page: https://github.com/deepshore/flasche
Author: deepshore
Author-email: github@deephore.de
License: UNKNOWN
Keywords: flask,web
Platform: UNKNOWN
Classifier: Development Status :: 3 - Alpha
Classifier: Intended Audience :: Developers
Classifier: License :: OSI Approved :: MIT License
Classifier: Programming Language :: Python :: 3
Requires-Python: >=3.6, <4
Requires-Dist: flask
Requires-Dist: flask-restx
Requires-Dist: prometheus-flask-exporter
